[
  {
    "N": 512,
    "dynamics": "Glauber",
    "ikBT": 1,
    "alpha_mean": 1.5243,
    "alpha_lower": 1.5157,
    "alpha_upper": 1.5323,
    "C_mean": -6.0937,
    "C_lower": -6.1629,
    "C_upper": -6.0133,
    "adjR2_mean": 0.9987,
    "adjR2_lower": 0.9985,
    "adjR2_upper": 0.9988,
    "xmin_mean": 6.0621,
    "xmin_lower": 6.0428,
    "xmin_upper": 6.0782,
    "optDs_mean": 1.8075,
    "optDs_lower": 1.7818,
    "optDs_upper": 1.834,
    "H": 0.92,
    "J": 1,
    "nrepeat": 40
  }
]
